LICENSE
MANIFEST.in
README.md
manage_lua_resty_fastutils.py
requirements.txt
setup.py
lua_resty_fastutils/__init__.py
lua_resty_fastutils.egg-info/PKG-INFO
lua_resty_fastutils.egg-info/SOURCES.txt
lua_resty_fastutils.egg-info/dependency_links.txt
lua_resty_fastutils.egg-info/entry_points.txt
lua_resty_fastutils.egg-info/not-zip-safe
lua_resty_fastutils.egg-info/requires.txt
lua_resty_fastutils.egg-info/top_level.txt
lua_resty_fastutils/src/.rockspec
lua_resty_fastutils/src/lua/resty/fastutils/httpclientutils.lua
lua_resty_fastutils/src/lua/resty/fastutils/kongutils.lua
lua_resty_fastutils/src/lua/resty/fastutils/redisutils.lua
lua_resty_fastutils/src/lua/test/redisutils.lua